yaml_combine-0.4.0-py3.10-nspkg.pth
randomnoun/yaml_combine/__init__.py
randomnoun/yaml_combine/__main__.py
randomnoun/yaml_combine/yaml_combiner.py
yaml_combine-0.4.0.dist-info/LICENSE.txt
yaml_combine-0.4.0.dist-info/METADATA
yaml_combine-0.4.0.dist-info/WHEEL
yaml_combine-0.4.0.dist-info/entry_points.txt
yaml_combine-0.4.0.dist-info/namespace_packages.txt
yaml_combine-0.4.0.dist-info/top_level.txt
yaml_combine-0.4.0.dist-info/RECORD
