Metadata-Version: 2.1
Name: yaml-combine
Version: 0.4.0
Summary: A YAML pre-processor to combine one or more YAML files with $xref references.
Home-page: https://github.com/randomnoun/yaml-combine-py
Author: Greg Knox
Author-email: knoxg+pypi@randomnoun.com
License: UNKNOWN
Project-URL: Bug Reports, https://github.com/randomnoun/yaml-combine-py/issues
Project-URL: Source, https://github.com/randomnoun/yaml-combine-py/
Keywords: yaml,combine
Platform: UNKNOWN
Classifier: Development Status :: 3 - Alpha
Classifier: Intended Audience :: Developers
Classifier: Topic :: Text Processing :: Markup
Classifier: License :: OSI Approved :: BSD License
Classifier: Programming Language :: Python :: 3
Classifier: Programming Language :: Python :: 3.6
Classifier: Programming Language :: Python :: 3.7
Classifier: Programming Language :: Python :: 3.8
Classifier: Programming Language :: Python :: 3.9
Classifier: Programming Language :: Python :: 3.10
Classifier: Programming Language :: Python :: 3 :: Only
Requires-Python: >=3.6, <4
License-File: LICENSE.txt
Requires-Dist: pyyaml
Provides-Extra: dev
Requires-Dist: check-manifest ; extra == 'dev'
Provides-Extra: test
Requires-Dist: coverage ; extra == 'test'
